{"chunk_definitions":[{"row":9,"row_count":1,"visible":true,"expansion_state":0,"options":{"engine":"r","label":"setup","include":false,"dev":"png"},"document_id":"2237E57E","chunk_id":"csetup_chunk","chunk_label":"setup"},{"row":20,"row_count":1,"visible":true,"expansion_state":0,"options":{"engine":"r","label":"unnamed-chunk-2","dev":"png"},"document_id":"2237E57E","chunk_id":"clh0rjbm3h4c0","chunk_label":"unnamed-chunk-1"},{"row":25,"row_count":1,"visible":true,"expansion_state":0,"options":{"engine":"r","label":"unnamed-chunk-5","dev":"png"},"document_id":"2237E57E","chunk_id":"ctnjh473952r2","chunk_label":"unnamed-chunk-2"},{"row":32,"row_count":1,"visible":true,"expansion_state":0,"options":{"engine":"r","label":"unnamed-chunk-7","dev":"png"},"document_id":"2237E57E","chunk_id":"crz7yc8sua7ke","chunk_label":"unnamed-chunk-3"}],"doc_write_time":1725566334,"working_dir":null,"default_chunk_options":{"echo":true}}